builder_maid/__init__.py
builder_maid/target.py
builder_maid-0.2.3.dist-info/METADATA
builder_maid-0.2.3.dist-info/WHEEL
builder_maid-0.2.3.dist-info/licenses/LICENSE
builder_maid-0.2.3.dist-info/RECORD
